aind_behavior_curriculum_template/__init__.py
aind_behavior_curriculum_template/upload.py
aind_behavior_curriculum_template-0.0.4.dist-info/LICENSE
aind_behavior_curriculum_template-0.0.4.dist-info/METADATA
aind_behavior_curriculum_template-0.0.4.dist-info/WHEEL
aind_behavior_curriculum_template-0.0.4.dist-info/top_level.txt
aind_behavior_curriculum_template-0.0.4.dist-info/RECORD
